{
  "project_info": {
    "project_number": "852874832270",
    "project_id": "snapshots-56a56",
    "storage_bucket": "snapshots-56a56.appspot.com"
  },
  "client": [
    {
      "client_info": {
        "mobilesdk_app_id": "1:852874832270:android:374b709da5ffec04ea5cdf",
        "android_client_info": {
          "package_name": "com.example.snapshots"
        }
      },
      "oauth_client": [
        {
          "client_id": "852874832270-hes2lntburvg6jfeqnb0icup3bcsahu4.apps.googleusercontent.com",
          "client_type": 3
        }
      ],
      "api_key": [
        {
          "current_key": "AIzaSyAQmosAvq8T84Mz0wrxkRwnWREvhkkL_BY"
        }
      ],
      "services": {
        "appinvite_service": {
          "other_platform_oauth_client": [
            {
              "client_id": "852874832270-hes2lntburvg6jfeqnb0icup3bcsahu4.apps.googleusercontent.com",
              "client_type": 3
            }
          ]
        }
      }
    }
  ],
  "configuration_version": "1"
}